dict_to_protobuf.py
dict_to_protobuf-0.0.3.10.dist-info/LICENSE
dict_to_protobuf-0.0.3.10.dist-info/METADATA
dict_to_protobuf-0.0.3.10.dist-info/WHEEL
dict_to_protobuf-0.0.3.10.dist-info/top_level.txt
dict_to_protobuf-0.0.3.10.dist-info/RECORD
